{
    "swagger": "2.0",
    "info": {
        "version": "$version",
        "title": "$title"
    },
    "basePath": "/",
    "schemes": [
        "https"
    ],
    "paths": {
        "/$basePath": {
            "options": {
                "consumes": [
                    "application/json"
                ],
                "produces": [
                    "application/json"
                ],
                "responses": {
                    "200": {
                        "description": "200 response",
                        "schema": {
                            "$ref": "#/definitions/Empty"
                        },
                        "headers": {
                            "Access-Control-Allow-Origin": {
                                "type": "string"
                            },
                            "Access-Control-Allow-Methods": {
                                "type": "string"
                            },
                            "Access-Control-Allow-Headers": {
                                "type": "string"
                            }
                        }
                    }
                },
                "x-amazon-apigateway-integration": {
                    "responses": {
                        "default": {
                            "statusCode": "200",
                            "responseParameters": {
                                "method.response.header.Access-Control-Allow-Methods": "'DELETE,GET,HEAD,OPTIONS,PATCH,POST,PUT'",
                                "method.response.header.Access-Control-Allow-Headers": "'Content-Type,Authorization,X-Amz-Date,X-Api-Key,X-Amz-Security-Token,x-requested-with'",
                                "method.response.header.Access-Control-Allow-Origin": "'*'"
                            }
                        }
                    },
                    "requestTemplates": {
                        "application/json": "{\"statusCode\": 200}"
                    },
                    "passthroughBehavior": "when_no_match",
                    "type": "mock"
                }
            },
      
            "x-amazon-apigateway-any-method": {
                "produces": [
                    "application/json"
                ],
                "security": [$authorizer],
                "responses": {
                    "200": {
                        "description": "200 response",
                        "schema": {
                            "$ref": "#/definitions/Empty"
                        }
                    }
                },
                "x-amazon-apigateway-integration": {
                    "responses": {
                        "default": {
                            "statusCode": "200"
                        }
                    },
                    "uri": "arn:aws:apigateway:$apiRegion:lambda:path/2015-03-31/functions/arn:aws:lambda:$functionRegion:$accountId:function:$functionName/invocations",
                    "passthroughBehavior": "when_no_match",
                    "httpMethod": "POST",
                    "contentHandling": "CONVERT_TO_TEXT",
                    "type": "aws_proxy",
                    "credentials": "$credentials"
                }
            }
        },

        "/$basePath/{proxy+}": {
            "options": {
                "consumes": [
                    "application/json"
                ],
                "produces": [
                    "application/json"
                ],
                "responses": {
                    "200": {
                        "description": "200 response",
                        "schema": {
                            "$ref": "#/definitions/Empty"
                        },
                        "headers": {
                            "Access-Control-Allow-Origin": {
                                "type": "string"
                            },
                            "Access-Control-Allow-Methods": {
                                "type": "string"
                            },
                            "Access-Control-Allow-Headers": {
                                "type": "string"
                            }
                        }
                    }
                },
                "x-amazon-apigateway-integration": {
                    "responses": {
                        "default": {
                            "statusCode": "200",
                            "responseParameters": {
                                "method.response.header.Access-Control-Allow-Methods": "'DELETE,GET,HEAD,OPTIONS,PATCH,POST,PUT'",
                                "method.response.header.Access-Control-Allow-Headers": "'Content-Type,Authorization,X-Amz-Date,X-Api-Key,X-Amz-Security-Token,x-requested-with'",
                                "method.response.header.Access-Control-Allow-Origin": "'*'"
                            }
                        }
                    },
                    "requestTemplates": {
                        "application/json": "{\"statusCode\": 200}"
                    },
                    "passthroughBehavior": "when_no_match",
                    "type": "mock"
                }
            },
            
            "x-amazon-apigateway-any-method": {
                "produces": [
                    "application/json"
                ],
                "security": [$authorizer],
                "parameters": [
                    {
                        "name": "proxy",
                        "in": "path",
                        "required": true,
                        "type": "string"
                    }
                ],
                "responses": {
                },
                "x-amazon-apigateway-integration": {
                    "responses": {
                        "default": {
                            "statusCode": "200"
                        }
                    },
                    "uri": "arn:aws:apigateway:$apiRegion:lambda:path/2015-03-31/functions/arn:aws:lambda:$functionRegion:$accountId:function:$functionName/invocations",
                    "passthroughBehavior": "when_no_match",
                    "httpMethod": "POST",
                    "cacheKeyParameters": [
                        "method.request.path.proxy"
                    ],
                    "contentHandling": "CONVERT_TO_TEXT",
                    "type": "aws_proxy",
                    "credentials": "$credentials"
                }
            }
        }
    },
    "definitions": {
        "Empty": {
            "type": "object"
        }
    }

    $securityDefinitions
}
